toolkit/__init__.py
toolkit/behaviour/__init__.py
toolkit/behaviour/command.py
toolkit/behaviour/cor.py
toolkit/behaviour/mediator.py
toolkit/behaviour/mementos.py
toolkit/behaviour/observer.py
toolkit/behaviour/state.py
toolkit/creation/__init__.py
toolkit/creation/factory.py
toolkit/creation/singleton.py
toolkit/tests/__init__.py
toolkit/tests/test_command.py
toolkit/tests/test_cor.py
toolkit/tests/test_factory.py
toolkit/tests/test_mediator.py
toolkit/tests/test_mementos.py
toolkit/tests/test_observer.py
toolkit/tests/test_singleton.py
toolkit/tests/test_state.py
design_pattern_toolkit-1.0a2.dist-info/LICENSE.txt
design_pattern_toolkit-1.0a2.dist-info/METADATA
design_pattern_toolkit-1.0a2.dist-info/WHEEL
design_pattern_toolkit-1.0a2.dist-info/top_level.txt
design_pattern_toolkit-1.0a2.dist-info/RECORD
